oe_python_template/__init__.py
oe_python_template/api.py
oe_python_template/cli.py
oe_python_template/constants.py
oe_python_template/hello/__init__.py
oe_python_template/hello/_api.py
oe_python_template/hello/_cli.py
oe_python_template/hello/_constants.py
oe_python_template/hello/_gui.py
oe_python_template/hello/_models.py
oe_python_template/hello/_service.py
oe_python_template/hello/_settings.py
oe_python_template/system/__init__.py
oe_python_template/system/_api.py
oe_python_template/system/_cli.py
oe_python_template/system/_gui.py
oe_python_template/system/_service.py
oe_python_template/system/_settings.py
oe_python_template/utils/__init__.py
oe_python_template/utils/_api.py
oe_python_template/utils/_cli.py
oe_python_template/utils/_console.py
oe_python_template/utils/_constants.py
oe_python_template/utils/_di.py
oe_python_template/utils/_gui.py
oe_python_template/utils/_health.py
oe_python_template/utils/_log.py
oe_python_template/utils/_logfire.py
oe_python_template/utils/_notebook.py
oe_python_template/utils/_process.py
oe_python_template/utils/_sentry.py
oe_python_template/utils/_service.py
oe_python_template/utils/_settings.py
oe_python_template/utils/boot.py
oe_python_template/utils/.vendored/bottle.py
oe_python_template-0.17.10.dist-info/METADATA
oe_python_template-0.17.10.dist-info/WHEEL
oe_python_template-0.17.10.dist-info/entry_points.txt
oe_python_template-0.17.10.dist-info/licenses/LICENSE
oe_python_template-0.17.10.dist-info/RECORD
