Metadata-Version: 2.4
Name: oe-python-template
Version: 0.17.10
Summary: 🧠 Copier template to scaffold Python projects compliant with best practices and modern tooling.
Project-URL: Homepage, https://oe-python-template.readthedocs.io/en/latest/
Project-URL: Documentation, https://oe-python-template.readthedocs.io/en/latest/
Project-URL: Source, https://github.com/helmut-hoffer-von-ankershoffen/oe-python-template
Project-URL: Changelog, https://github.com/helmut-hoffer-von-ankershoffen/oe-python-template/releases
Project-URL: Issues, https://github.com/helmut-hoffer-von-ankershoffen/oe-python-template/issues
Author-email: Helmut Hoffer von Ankershoffen <helmuthva@gmail.com>
License: MIT License
License-File: LICENSE
Keywords: act,codecov,copier,cyclonedx,detect-secrets,devcontainer,docker,git-cliff,jupyter,marimo,mypy,nox,oe-python-template,pip-audit,pip-licenses,pre-commit,pydantic,pypi,pytest,python,readthedocs,ruff,sonarcloud,sonarqube,sphinx,streamlit,typer,uv
Classifier: Development Status :: 2 - Pre-Alpha
Classifier: Framework :: Pydantic
Classifier: Framework :: Pytest
Classifier: Intended Audience :: Developers
Classifier: Intended Audience :: End Users/Desktop
Classifier: License :: OSI Approved :: MIT License
Classifier: Natural Language :: English
Classifier: Operating System :: MacOS :: MacOS X
Classifier: Operating System :: Microsoft :: Windows
Classifier: Operating System :: POSIX :: Linux
Classifier: Programming Language :: Python
Classifier: Programming Language :: Python :: 3
Classifier: Programming Language :: Python :: 3.11
Classifier: Programming Language :: Python :: 3.12
Classifier: Programming Language :: Python :: 3.13
Classifier: Typing :: Typed
Requires-Python: <4.0,>=3.11
Requires-Dist: fastapi[all,standard]>=0.115.12
Requires-Dist: logfire[system-metrics]>=3.14.1
Requires-Dist: nicegui[native]>=2.15.0
Requires-Dist: opentelemetry-instrumentation-fastapi>=0.53b0
Requires-Dist: opentelemetry-instrumentation-httpx>=0.53b0
Requires-Dist: opentelemetry-instrumentation-jinja2>=0.53b0
Requires-Dist: opentelemetry-instrumentation-requests>=0.53b0
Requires-Dist: opentelemetry-instrumentation-sqlite3>=0.53b0
Requires-Dist: opentelemetry-instrumentation-tornado>=0.53b0
Requires-Dist: opentelemetry-instrumentation-urllib3>=0.53b0
Requires-Dist: opentelemetry-instrumentation-urllib>=0.53b0
Requires-Dist: psutil>=7.0.0
Requires-Dist: pydantic-settings>=2.9.1
Requires-Dist: pywin32>=310; sys_platform == 'win32'
Requires-Dist: sentry-sdk>=2.27.0
Requires-Dist: typer>=0.15.1
Requires-Dist: uptime>=3.0.1
Provides-Extra: examples
Requires-Dist: jinja2>=3.1.6; extra == 'examples'
Requires-Dist: jupyter>=1.1.1; extra == 'examples'
Requires-Dist: marimo>=0.13.1; extra == 'examples'
Requires-Dist: matplotlib>=3.10.1; extra == 'examples'
Requires-Dist: streamlit>=1.44.1; extra == 'examples'
